{"trial_id": "1", "hyperparameters": {"space": [{"class_name": "Choice", "config": {"name": "learning_rate", "default": 1e-05, "conditions": [], "values": [1e-05, 1e-06, 1e-07, 1e-08], "ordered": true}}], "values": {"learning_rate": 1e-05}}, "metrics": {"metrics": {"loss": {"direction": "min", "observations": [{"value": [0.619297444820404], "step": 99}]}, "accuracy": {"direction": "max", "observations": [{"value": [0.6811581254005432], "step": 99}]}, "val_loss": {"direction": "min", "observations": [{"value": [0.6274328231811523], "step": 99}]}, "val_accuracy": {"direction": "max", "observations": [{"value": [0.6821677088737488], "step": 99}]}}}, "score": 0.6274328231811523, "best_step": 99, "status": "COMPLETED", "message": null}